{
  "version": 1,
  "request_id": "20260515T172440_961189Z-vmi2737474",
  "status": "success",
  "completed_at_utc": "2026-05-15T17:25:07.315829+00:00",
  "item": "M4A4 | Desolate Space (Battle-Scarred)",
  "latest_sales": {
    "version": 1,
    "source": "network",
    "item": "M4A4 | Desolate Space (Battle-Scarred)",
    "url": "https://csfloat.com/api/v1/history/M4A4%20%7C%20Desolate%20Space%20%28Battle-Scarred%29/sales",
    "fetched_at_utc": "2026-05-15T17:25:07.314987+00:00",
    "raw_row_count": 40,
    "reference_currency": "USD",
    "fx_usd_to_eur": 0.85999,
    "fx_source": "Frankfurter 2026-05-15 (ECB)",
    "sales_rows": [
      {
        "sale_id": "975344784162029570",
        "sold_at": "2026-05-15T10:33:22.153965Z",
        "price_usd": 11.4,
        "price_eur": 9.8,
        "reference_currency": "USD",
        "fx_usd_to_eur": 0.85999,
        "fx_source": "Frankfurter 2026-05-15 (ECB)",
        "float_value": 0.5877826809883118,
        "paint_seed": 96,
        "stickers": [],
        "notes": []
      },
      {
        "sale_id": "973627818875423838",
        "sold_at": "2026-05-15T07:15:37.552597Z",
        "price_usd": 11.66,
        "price_eur": 10.03,
        "reference_currency": "USD",
        "fx_usd_to_eur": 0.85999,
        "fx_source": "Frankfurter 2026-05-15 (ECB)",
        "float_value": 0.5381776094436646,
        "paint_seed": 555,
        "stickers": [],
        "notes": []
      },
      {
        "sale_id": "975111981243695523",
        "sold_at": "2026-05-14T21:49:18.518777Z",
        "price_usd": 11.66,
        "price_eur": 10.03,
        "reference_currency": "USD",
        "fx_usd_to_eur": 0.85999,
        "fx_source": "Frankfurter 2026-05-15 (ECB)",
        "float_value": 0.7087689638137817,
        "paint_seed": 378,
        "stickers": [
          "Sticker | Ninjas in Pyjamas (Holo) | Antwerp 2022",
          "Sticker | BUDA | Rio 2022",
          "Sticker | oSee | Rio 2022",
          "Sticker | degster | Rio 2022"
        ],
        "notes": [
          "4 stickers"
        ]
      },
      {
        "sale_id": "972216333313902015",
        "sold_at": "2026-05-14T16:55:43.859957Z",
        "price_usd": 12.3,
        "price_eur": 10.58,
        "reference_currency": "USD",
        "fx_usd_to_eur": 0.85999,
        "fx_source": "Frankfurter 2026-05-15 (ECB)",
        "float_value": 0.7074242234230042,
        "paint_seed": 314,
        "stickers": [],
        "notes": []
      },
      {
        "sale_id": "973934436993337650",
        "sold_at": "2026-05-14T15:33:23.842946Z",
        "price_usd": 12.0,
        "price_eur": 10.32,
        "reference_currency": "USD",
        "fx_usd_to_eur": 0.85999,
        "fx_source": "Frankfurter 2026-05-15 (ECB)",
        "float_value": 0.5793604254722595,
        "paint_seed": 459,
        "stickers": [],
        "notes": []
      },
      {
        "sale_id": "975045620811304258",
        "sold_at": "2026-05-14T14:54:41.124546Z",
        "price_usd": 12.15,
        "price_eur": 10.45,
        "reference_currency": "USD",
        "fx_usd_to_eur": 0.85999,
        "fx_source": "Frankfurter 2026-05-15 (ECB)",
        "float_value": 0.957552433013916,
        "paint_seed": 215,
        "stickers": [],
        "notes": []
      },
      {
        "sale_id": "974932309448986219",
        "sold_at": "2026-05-14T14:12:24.909188Z",
        "price_usd": 15.49,
        "price_eur": 13.32,
        "reference_currency": "USD",
        "fx_usd_to_eur": 0.85999,
        "fx_source": "Frankfurter 2026-05-15 (ECB)",
        "float_value": 0.9988014698028564,
        "paint_seed": 652,
        "stickers": [
          "Sticker | broky (Glitter, Champion) | Antwerp 2022",
          "Sticker | Skelly Stabby"
        ],
        "notes": [
          "high #149",
          "2 stickers"
        ]
      },
      {
        "sale_id": "974442681864423865",
        "sold_at": "2026-05-13T23:51:37.414984Z",
        "price_usd": 12.12,
        "price_eur": 10.42,
        "reference_currency": "USD",
        "fx_usd_to_eur": 0.85999,
        "fx_source": "Frankfurter 2026-05-15 (ECB)",
        "float_value": 0.6013581156730652,
        "paint_seed": 926,
        "stickers": [
          "Sticker | GamerLegion | Paris 2023",
          "Sticker | GamerLegion | Paris 2023",
          "Sticker | drop | Antwerp 2022",
          "Sticker | Not For Resale"
        ],
        "notes": [
          "4 stickers"
        ]
      },
      {
        "sale_id": "973617727526798924",
        "sold_at": "2026-05-13T14:53:55.584777Z",
        "price_usd": 12.48,
        "price_eur": 10.73,
        "reference_currency": "USD",
        "fx_usd_to_eur": 0.85999,
        "fx_source": "Frankfurter 2026-05-15 (ECB)",
        "float_value": 0.501603364944458,
        "paint_seed": 713,
        "stickers": [
          "Sticker | Angry T"
        ],
        "notes": [
          "1 stickers"
        ]
      },
      {
        "sale_id": "974333975814343661",
        "sold_at": "2026-05-13T12:04:05.641329Z",
        "price_usd": 11.94,
        "price_eur": 10.27,
        "reference_currency": "USD",
        "fx_usd_to_eur": 0.85999,
        "fx_source": "Frankfurter 2026-05-15 (ECB)",
        "float_value": 0.47633108496665955,
        "paint_seed": 621,
        "stickers": [
          "Sticker | Team Spirit (Glitter) | Shanghai 2024"
        ],
        "notes": [
          "1 stickers"
        ]
      },
      {
        "sale_id": "974406760695728341",
        "sold_at": "2026-05-13T11:23:36.694018Z",
        "price_usd": 11.39,
        "price_eur": 9.8,
        "reference_currency": "USD",
        "fx_usd_to_eur": 0.85999,
        "fx_source": "Frankfurter 2026-05-15 (ECB)",
        "float_value": 0.5999665260314941,
        "paint_seed": 643,
        "stickers": [],
        "notes": []
      },
      {
        "sale_id": "973251692646760559",
        "sold_at": "2026-05-13T06:47:48.631975Z",
        "price_usd": 12.71,
        "price_eur": 10.93,
        "reference_currency": "USD",
        "fx_usd_to_eur": 0.85999,
        "fx_source": "Frankfurter 2026-05-15 (ECB)",
        "float_value": 0.7948851585388184,
        "paint_seed": 458,
        "stickers": [
          "Sticker | Hydro Stream",
          "Sticker | Hydro Stream",
          "Sticker | Hydro Wave",
          "Sticker | Hydro Wave",
          "Sticker | Hydro Wave"
        ],
        "notes": [
          "5 stickers"
        ]
      },
      {
        "sale_id": "974406228929285617",
        "sold_at": "2026-05-13T03:01:46.311909Z",
        "price_usd": 11.99,
        "price_eur": 10.31,
        "reference_currency": "USD",
        "fx_usd_to_eur": 0.85999,
        "fx_source": "Frankfurter 2026-05-15 (ECB)",
        "float_value": 0.8108490705490112,
        "paint_seed": 322,
        "stickers": [],
        "notes": []
      },
      {
        "sale_id": "974094828881185799",
        "sold_at": "2026-05-13T02:16:36.92265Z",
        "price_usd": 11.4,
        "price_eur": 9.8,
        "reference_currency": "USD",
        "fx_usd_to_eur": 0.85999,
        "fx_source": "Frankfurter 2026-05-15 (ECB)",
        "float_value": 0.561010479927063,
        "paint_seed": 857,
        "stickers": [
          "Sticker | Perry"
        ],
        "notes": [
          "1 stickers"
        ]
      },
      {
        "sale_id": "974396027698282934",
        "sold_at": "2026-05-12T19:55:46.522754Z",
        "price_usd": 11.18,
        "price_eur": 9.61,
        "reference_currency": "USD",
        "fx_usd_to_eur": 0.85999,
        "fx_source": "Frankfurter 2026-05-15 (ECB)",
        "float_value": 0.5264397859573364,
        "paint_seed": 948,
        "stickers": [],
        "notes": []
      },
      {
        "sale_id": "974387362593376460",
        "sold_at": "2026-05-12T19:39:02.011907Z",
        "price_usd": 11.93,
        "price_eur": 10.26,
        "reference_currency": "USD",
        "fx_usd_to_eur": 0.85999,
        "fx_source": "Frankfurter 2026-05-15 (ECB)",
        "float_value": 0.5154248476028442,
        "paint_seed": 446,
        "stickers": [
          "Sticker | G2 esports | Budapest 2025",
          "Sticker | Team Spirit | Budapest 2025",
          "Sticker | G2 esports | Budapest 2025",
          "Sticker | Team Spirit | Budapest 2025"
        ],
        "notes": [
          "4 stickers"
        ]
      },
      {
        "sale_id": "973341559032514137",
        "sold_at": "2026-05-12T18:24:17.211836Z",
        "price_usd": 12.08,
        "price_eur": 10.39,
        "reference_currency": "USD",
        "fx_usd_to_eur": 0.85999,
        "fx_source": "Frankfurter 2026-05-15 (ECB)",
        "float_value": 0.5955188274383545,
        "paint_seed": 257,
        "stickers": [],
        "notes": []
      },
      {
        "sale_id": "974276576768295381",
        "sold_at": "2026-05-12T17:07:31.532723Z",
        "price_usd": 12.25,
        "price_eur": 10.53,
        "reference_currency": "USD",
        "fx_usd_to_eur": 0.85999,
        "fx_source": "Frankfurter 2026-05-15 (ECB)",
        "float_value": 0.5099740028381348,
        "paint_seed": 947,
        "stickers": [
          "Sticker | OG | Paris 2023",
          "Sticker | Spirit | 2020 RMR"
        ],
        "notes": [
          "2 stickers"
        ]
      },
      {
        "sale_id": "974289552820798467",
        "sold_at": "2026-05-12T15:30:10.93238Z",
        "price_usd": 12.21,
        "price_eur": 10.5,
        "reference_currency": "USD",
        "fx_usd_to_eur": 0.85999,
        "fx_source": "Frankfurter 2026-05-15 (ECB)",
        "float_value": 0.49042606353759766,
        "paint_seed": 879,
        "stickers": [],
        "notes": []
      },
      {
        "sale_id": "974246577700996816",
        "sold_at": "2026-05-12T09:48:05.297499Z",
        "price_usd": 12.27,
        "price_eur": 10.55,
        "reference_currency": "USD",
        "fx_usd_to_eur": 0.85999,
        "fx_source": "Frankfurter 2026-05-15 (ECB)",
        "float_value": 0.5656265020370483,
        "paint_seed": 676,
        "stickers": [
          "Sticker | Boost (Holo)",
          "Sticker | KSCERATO | Katowice 2019",
          "Sticker | EliGE (Foil) | Boston 2018"
        ],
        "notes": [
          "3 stickers"
        ]
      },
      {
        "sale_id": "974211926676603631",
        "sold_at": "2026-05-12T07:30:23.349007Z",
        "price_usd": 11.4,
        "price_eur": 9.8,
        "reference_currency": "USD",
        "fx_usd_to_eur": 0.85999,
        "fx_source": "Frankfurter 2026-05-15 (ECB)",
        "float_value": 0.47129499912261963,
        "paint_seed": 651,
        "stickers": [
          "Sticker | Delicious Tears"
        ],
        "notes": [
          "1 stickers"
        ]
      },
      {
        "sale_id": "973235628542132456",
        "sold_at": "2026-05-11T22:22:14.7835Z",
        "price_usd": 12.35,
        "price_eur": 10.62,
        "reference_currency": "USD",
        "fx_usd_to_eur": 0.85999,
        "fx_source": "Frankfurter 2026-05-15 (ECB)",
        "float_value": 0.5991489887237549,
        "paint_seed": 38,
        "stickers": [],
        "notes": []
      },
      {
        "sale_id": "973759318400828326",
        "sold_at": "2026-05-11T18:19:37.651124Z",
        "price_usd": 12.36,
        "price_eur": 10.63,
        "reference_currency": "USD",
        "fx_usd_to_eur": 0.85999,
        "fx_source": "Frankfurter 2026-05-15 (ECB)",
        "float_value": 0.5167439579963684,
        "paint_seed": 508,
        "stickers": [
          "Sticker | Unicorn (Holo)",
          "Sticker | Rush 4x20 (Holo)"
        ],
        "notes": [
          "2 stickers"
        ]
      },
      {
        "sale_id": "973995048314209590",
        "sold_at": "2026-05-11T17:48:51.13422Z",
        "price_usd": 11.3,
        "price_eur": 9.72,
        "reference_currency": "USD",
        "fx_usd_to_eur": 0.85999,
        "fx_source": "Frankfurter 2026-05-15 (ECB)",
        "float_value": 0.7618784308433533,
        "paint_seed": 270,
        "stickers": [
          "Sticker | Eternal Fire | Antwerp 2022"
        ],
        "notes": [
          "1 stickers"
        ]
      },
      {
        "sale_id": "973844941237256256",
        "sold_at": "2026-05-11T16:53:38.24935Z",
        "price_usd": 12.22,
        "price_eur": 10.51,
        "reference_currency": "USD",
        "fx_usd_to_eur": 0.85999,
        "fx_source": "Frankfurter 2026-05-15 (ECB)",
        "float_value": 0.8804315328598022,
        "paint_seed": 72,
        "stickers": [],
        "notes": []
      },
      {
        "sale_id": "973942596386818671",
        "sold_at": "2026-05-11T13:41:07.00547Z",
        "price_usd": 15.51,
        "price_eur": 13.34,
        "reference_currency": "USD",
        "fx_usd_to_eur": 0.85999,
        "fx_source": "Frankfurter 2026-05-15 (ECB)",
        "float_value": 0.998536229133606,
        "paint_seed": 255,
        "stickers": [
          "Sticker | Vitality (Holo) | Katowice 2019",
          "Sticker | Vitality (Holo) | Katowice 2019",
          "Sticker | Vitality (Holo) | Katowice 2019",
          "Sticker | Vitality (Holo) | Katowice 2019"
        ],
        "notes": [
          "high #182",
          "4 stickers"
        ]
      },
      {
        "sale_id": "973722073866306071",
        "sold_at": "2026-05-11T08:36:08.954831Z",
        "price_usd": 12.21,
        "price_eur": 10.5,
        "reference_currency": "USD",
        "fx_usd_to_eur": 0.85999,
        "fx_source": "Frankfurter 2026-05-15 (ECB)",
        "float_value": 0.4925416111946106,
        "paint_seed": 386,
        "stickers": [
          "Sticker | Ninjas in Pyjamas (Glitter) | Antwerp 2022",
          "Sticker | Ninjas in Pyjamas (Glitter) | Antwerp 2022"
        ],
        "notes": [
          "2 stickers"
        ]
      },
      {
        "sale_id": "973788179373100525",
        "sold_at": "2026-05-11T03:26:34.096743Z",
        "price_usd": 11.29,
        "price_eur": 9.71,
        "reference_currency": "USD",
        "fx_usd_to_eur": 0.85999,
        "fx_source": "Frankfurter 2026-05-15 (ECB)",
        "float_value": 0.6619415283203125,
        "paint_seed": 41,
        "stickers": [
          "Sticker | Counter-Tech"
        ],
        "notes": [
          "1 stickers"
        ]
      },
      {
        "sale_id": "973587374099530281",
        "sold_at": "2026-05-10T16:47:08.53641Z",
        "price_usd": 11.0,
        "price_eur": 9.46,
        "reference_currency": "USD",
        "fx_usd_to_eur": 0.85999,
        "fx_source": "Frankfurter 2026-05-15 (ECB)",
        "float_value": 0.8081318736076355,
        "paint_seed": 282,
        "stickers": [],
        "notes": []
      },
      {
        "sale_id": "973414588563456226",
        "sold_at": "2026-05-10T11:07:58.299124Z",
        "price_usd": 12.29,
        "price_eur": 10.57,
        "reference_currency": "USD",
        "fx_usd_to_eur": 0.85999,
        "fx_source": "Frankfurter 2026-05-15 (ECB)",
        "float_value": 0.9312672019004822,
        "paint_seed": 969,
        "stickers": [
          "Sticker | G2 Esports | Stockholm 2021",
          "Sticker | VINI | Stockholm 2021",
          "Sticker | Team Liquid | Stockholm 2021"
        ],
        "notes": [
          "3 stickers"
        ]
      }
    ]
  }
}
